parcelpending/__init__.py
parcelpending/cli.py
parcelpending/client.py
parcelpending/exceptions.py
parcelpending/utils.py
tests/__init__.py
tests/test_client.py
parcelpending-1.0.0.dist-info/LICENSE
parcelpending-1.0.0.dist-info/METADATA
parcelpending-1.0.0.dist-info/WHEEL
parcelpending-1.0.0.dist-info/entry_points.txt
parcelpending-1.0.0.dist-info/top_level.txt
parcelpending-1.0.0.dist-info/RECORD
